wyrestorm_networkhd/__init__.py
wyrestorm_networkhd/_version.py
wyrestorm_networkhd/exceptions.py
wyrestorm_networkhd/logging_config.py
wyrestorm_networkhd/py.typed
wyrestorm_networkhd/commands/__init__.py
wyrestorm_networkhd/commands/_response_helpers.py
wyrestorm_networkhd/commands/api_endpoint.py
wyrestorm_networkhd/commands/api_notifications.py
wyrestorm_networkhd/commands/api_query.py
wyrestorm_networkhd/commands/audio_output.py
wyrestorm_networkhd/commands/connected_device_control.py
wyrestorm_networkhd/commands/device_port_switch.py
wyrestorm_networkhd/commands/media_stream_matrix_switch.py
wyrestorm_networkhd/commands/multiview.py
wyrestorm_networkhd/commands/reboot_reset.py
wyrestorm_networkhd/commands/video_stream_text_overlay.py
wyrestorm_networkhd/commands/video_wall.py
wyrestorm_networkhd/core/__init__.py
wyrestorm_networkhd/core/_client.py
wyrestorm_networkhd/core/client_rs232.py
wyrestorm_networkhd/core/client_ssh.py
wyrestorm_networkhd/models/__init__.py
wyrestorm_networkhd/models/api_notifications.py
wyrestorm_networkhd/models/api_query.py
wyrestorm_networkhd-2.2.1.dist-info/licenses/LICENSE
wyrestorm_networkhd-2.2.1.dist-info/METADATA
wyrestorm_networkhd-2.2.1.dist-info/WHEEL
wyrestorm_networkhd-2.2.1.dist-info/top_level.txt
wyrestorm_networkhd-2.2.1.dist-info/RECORD
