Metadata-Version: 2.4
Name: wyrestorm-networkhd
Version: 2.2.1
Summary: Python client library for WyreStorm NetworkHD API operations - matrix switching, device control, video walls, and multiview.
Author-email: Matt-Hadley <81762940+Matt-Hadley@users.noreply.github.com>
Project-URL: Homepage, https://github.com/Matt-Hadley/wyrestorm-networkhd-py
Project-URL: Repository, https://github.com/Matt-Hadley/wyrestorm-networkhd-py.git
Project-URL: Issues, https://github.com/Matt-Hadley/wyrestorm-networkhd-py/issues
Project-URL: Documentation, https://matt-hadley.github.io/wyrestorm-networkhd-py/
Project-URL: Changelog, https://matt-hadley.github.io/wyrestorm-networkhd-py/changelog/
Keywords: wyrestorm,networkhd,api,matrix,switching,video,wall,multiview,hdmi,av,control
Classifier: Development Status :: 5 - Production/Stable
Classifier: Intended Audience :: Developers
Classifier: Intended Audience :: System Administrators
Classifier: Operating System :: OS Independent
Classifier: Programming Language :: Python :: 3
Classifier: Programming Language :: Python :: 3.11
Classifier: Programming Language :: Python :: 3.12
Classifier: Programming Language :: Python :: 3.13
Classifier: Topic :: Software Development :: Libraries :: Python Modules
Classifier: Topic :: System :: Hardware
Classifier: Topic :: System :: Networking
Classifier: Topic :: Multimedia :: Video
Requires-Python: >=3.11
License-File: LICENSE
Requires-Dist: paramiko>=3.0.0
Provides-Extra: dev
Requires-Dist: ruff>=0.12.10; extra == "dev"
Requires-Dist: pytest>=8.4.1; extra == "dev"
Requires-Dist: pytest-cov>=6.0.0; extra == "dev"
Requires-Dist: pytest-asyncio>=1.0.0; extra == "dev"
Requires-Dist: pytest-mock>=3.12.0; extra == "dev"
Requires-Dist: bandit[toml]>=1.7.0; extra == "dev"
Requires-Dist: pip-audit>=2.6.0; extra == "dev"
Requires-Dist: mypy>=1.8.0; extra == "dev"
Requires-Dist: build>=1.0.0; extra == "dev"
Requires-Dist: twine>=6.1.0; extra == "dev"
Requires-Dist: pre-commit>=3.6.0; extra == "dev"
Requires-Dist: vulture>=2.1.4; extra == "dev"
Requires-Dist: pyupgrade>=3.10.0; extra == "dev"
Requires-Dist: setuptools-scm>=8.1.0; extra == "dev"
Requires-Dist: async-pyserial>=0.1.0; extra == "dev"
Requires-Dist: paramiko>=3.0.0; extra == "dev"
Provides-Extra: rs232
Requires-Dist: async-pyserial>=0.1.0; extra == "rs232"
Provides-Extra: docs
Requires-Dist: mkdocs>=1.6.0; extra == "docs"
Requires-Dist: mkdocs-material>=9.5.0; extra == "docs"
Requires-Dist: mkdocstrings[python]>=0.26.0; extra == "docs"
Requires-Dist: mkdocs-include-markdown-plugin>=6.2.0; extra == "docs"
Requires-Dist: mkdocs-macros-plugin>=1.3.0; extra == "docs"
Dynamic: license-file
